odoo9_addon_purchase_requisition_operating_unit-9.0.1.0.0.99.dev6-py2.7-nspkg.pth
odoo9_addon_purchase_requisition_operating_unit-9.0.1.0.0.99.dev6.dist-info/METADATA
odoo9_addon_purchase_requisition_operating_unit-9.0.1.0.0.99.dev6.dist-info/RECORD
odoo9_addon_purchase_requisition_operating_unit-9.0.1.0.0.99.dev6.dist-info/WHEEL
odoo9_addon_purchase_requisition_operating_unit-9.0.1.0.0.99.dev6.dist-info/namespace_packages.txt
odoo9_addon_purchase_requisition_operating_unit-9.0.1.0.0.99.dev6.dist-info/top_level.txt
odoo_addons/purchase_requisition_operating_unit/README.rst
odoo_addons/purchase_requisition_operating_unit/__init__.py
odoo_addons/purchase_requisition_operating_unit/__openerp__.py
odoo_addons/purchase_requisition_operating_unit/model/__init__.py
odoo_addons/purchase_requisition_operating_unit/model/purchase_requisition.py
odoo_addons/purchase_requisition_operating_unit/security/purchase_security.xml
odoo_addons/purchase_requisition_operating_unit/static/description/icon.png
odoo_addons/purchase_requisition_operating_unit/tests/__init__.py
odoo_addons/purchase_requisition_operating_unit/tests/test_purchase_requisition_operating_unit.py
odoo_addons/purchase_requisition_operating_unit/view/purchase_requisition.xml
